<?xml version="1.0" encoding="utf-8" standalone="yes"?>

<item>
<title>[COLOR gold][B]Ep1: Salvador[/B][/COLOR]</title>
<link>http://vd.ec.cx/vd/dd/RC/RCServer01/videos/SMLLVLT09EP01.mp4</link>
<thumbnail>http://i.imgur.com/5htLqHK.jpg</thumbnail>
<fanart>https://goo.gl/fBFyWB</fanart>
<info>[COLOR blue]Uma interpretação da história de Superman mostra o jovem Clark Kent aprendendo a usar seus superpoderes em Kansas.[/COLOR]</info>
</item>


<item>
<title>[COLOR gold][B]Ep2: Metallo [/B][/COLOR]</title>
<link>http://vd.ec.cx/vd/dd/RC/RCServer01/videos/SMLLVLT09EP02.mp4</link>
<thumbnail>http://i.imgur.com/5htLqHK.jpg</thumbnail>
<fanart>https://goo.gl/fBFyWB</fanart>
<info>[COLOR blue]Uma interpretação da história de Superman mostra o jovem Clark Kent aprendendo a usar seus superpoderes em Kansas.[/COLOR]</info>
</item>


<item>
<title>[COLOR gold][B]Ep3: Raiva [/B][/COLOR]</title>
<link>http://vd.ec.cx/vd/dd/RC/RCServer01/videos/SMLLVLT09EP03.mp4</link>
<thumbnail>http://i.imgur.com/5htLqHK.jpg</thumbnail>
<fanart>https://goo.gl/fBFyWB</fanart>
<info>[COLOR blue]Uma interpretação da história de Superman mostra o jovem Clark Kent aprendendo a usar seus superpoderes em Kansas.[/COLOR]</info>
</item>


<item>
<title>[COLOR gold][B]Ep4: Eco [/B][/COLOR]</title>
<link>http://vd.ec.cx/vd/dd/RC/RCServer01/videos/SMLLVLT09EP04.mp4</link>
<thumbnail>http://i.imgur.com/5htLqHK.jpg</thumbnail>
<fanart>https://goo.gl/fBFyWB</fanart>
<info>[COLOR blue]Uma interpretação da história de Superman mostra o jovem Clark Kent aprendendo a usar seus superpoderes em Kansas.[/COLOR]</info>
</item>

<item>
<title>[COLOR gold][B]Ep5: Roleta [/B][/COLOR]</title>
<link>http://vd.ec.cx/vd/dd/RC/RCServer01/videos/SMLLVLT09EP05.mp4</link>
<thumbnail>http://i.imgur.com/5htLqHK.jpg</thumbnail>
<fanart>https://goo.gl/fBFyWB</fanart>
<info>[COLOR blue]Uma interpretação da história de Superman mostra o jovem Clark Kent aprendendo a usar seus superpoderes em Kansas.[/COLOR]</info>
</item>


<item>
<title>[COLOR gold][B]Ep6: Fogo Cruzado [/B][/COLOR]</title>
<link>http://vd.ec.cx/vd/dd/RC/RCServer01/videos/SMLLVLT09EP06.mp4</link>
<thumbnail>http://i.imgur.com/5htLqHK.jpg</thumbnail>
<fanart>https://goo.gl/fBFyWB</fanart>
<info>[COLOR blue]Uma interpretação da história de Superman mostra o jovem Clark Kent aprendendo a usar seus superpoderes em Kansas.[/COLOR]</info>
</item>


<item>
<title>[COLOR gold][B]Ep7: Kandor [/B][/COLOR]</title>
<link>http://vd.ec.cx/vd/dd/RC/RCServer01/videos/SMLLVLT09EP07.mp4</link>
<thumbnail>http://i.imgur.com/5htLqHK.jpg</thumbnail>
<fanart>https://goo.gl/fBFyWB</fanart>
<info>[COLOR blue]Uma interpretação da história de Superman mostra o jovem Clark Kent aprendendo a usar seus superpoderes em Kansas.[/COLOR]</info>
</item>

<item>
<title>[COLOR gold][B]Ep8: Ídolo [/B][/COLOR]</title>
<link>http://vd.ec.cx/vd/dd/RC/RCServer01/videos/SMLLVLT09EP08.mp4</link>
<thumbnail>http://i.imgur.com/5htLqHK.jpg</thumbnail>
<fanart>https://goo.gl/fBFyWB</fanart>
<info>[COLOR blue]Uma interpretação da história de Superman mostra o jovem Clark Kent aprendendo a usar seus superpoderes em Kansas.[/COLOR]</info>
</item>


<item>
<title>[COLOR gold][B]Ep9: Pandora [/B][/COLOR]</title>
<link>http://vd.ec.cx/vd/dd/RC/RCServer01/videos/SMLLVLT09EP09.mp4</link>
<thumbnail>http://i.imgur.com/5htLqHK.jpg</thumbnail>
<fanart>https://goo.gl/fBFyWB</fanart>
<info>[COLOR blue]Uma interpretação da história de Superman mostra o jovem Clark Kent aprendendo a usar seus superpoderes em Kansas.[/COLOR]</info>
</item>


<item>
<title>[COLOR gold][B]Ep10: Discípulo [/B][/COLOR]</title>
<link>http://vd.ec.cx/vd/dd/RC/RCServer01/videos/SMLLVLT09EP10.mp4</link>
<thumbnail>http://i.imgur.com/5htLqHK.jpg</thumbnail>
<fanart>https://goo.gl/fBFyWB</fanart>
<info>[COLOR blue]Uma interpretação da história de Superman mostra o jovem Clark Kent aprendendo a usar seus superpoderes em Kansas.[/COLOR]</info>
</item>


<item>
<title>[COLOR gold][B]Ep11: Sociedade  [/B][/COLOR]</title>
<link>http://vd.ec.cx/vd/dd/RC/RCServer01/videos/SMLLVLT09EP11.mp4</link>
<thumbnail>http://i.imgur.com/5htLqHK.jpg</thumbnail>
<fanart>https://goo.gl/fBFyWB</fanart>
<info>[COLOR blue]Uma interpretação da história de Superman mostra o jovem Clark Kent aprendendo a usar seus superpoderes em Kansas.[/COLOR]</info>
</item>


<item>
<title>[COLOR gold][B]Ep12: Guerreiro [/B][/COLOR]</title>
<link>http://vd.ec.cx/vd/dd/RC/RCServer01/videos/SMLLVLT09EP12.mp4</link>
<thumbnail>http://i.imgur.com/5htLqHK.jpg</thumbnail>
<fanart>https://goo.gl/fBFyWB</fanart>
<info>[COLOR blue]Uma interpretação da história de Superman mostra o jovem Clark Kent aprendendo a usar seus superpoderes em Kansas.[/COLOR]</info>
</item>


<item>
<title>[COLOR gold][B]Ep13: Persuasão [/B][/COLOR]</title>
<link>http://vd.ec.cx/vd/dd/RC/RCServer01/videos/SMLLVLT09EP13.mp4</link>
<thumbnail>http://i.imgur.com/5htLqHK.jpg</thumbnail>
<fanart>https://goo.gl/fBFyWB</fanart>
<info>[COLOR blue]Uma interpretação da história de Superman mostra o jovem Clark Kent aprendendo a usar seus superpoderes em Kansas.[/COLOR]</info>
</item>


<item>
<title>[COLOR gold][B]Ep14: Conspiração [/B][/COLOR]</title>
<link>http://vd.ec.cx/vd/dd/RC/RCServer01/videos/SMLLVLT09EP14.mp4</link>
<thumbnail>http://i.imgur.com/5htLqHK.jpg</thumbnail>
<fanart>https://goo.gl/fBFyWB</fanart>
<info>[COLOR blue]Uma interpretação da história de Superman mostra o jovem Clark Kent aprendendo a usar seus superpoderes em Kansas.[/COLOR]</info>
</item>


<item>
<title>[COLOR gold][B]Ep15: Fuga romântica[/B][/COLOR]</title>
<link>http://vd.ec.cx/vd/dd/RC/RCServer01/videos/SMLLVLT09EP15.mp4</link>
<thumbnail>http://i.imgur.com/5htLqHK.jpg</thumbnail>
<fanart>https://goo.gl/fBFyWB</fanart>
<info>[COLOR blue]Uma interpretação da história de Superman mostra o jovem Clark Kent aprendendo a usar seus superpoderes em Kansas.[/COLOR]</info>
</item>


<item>
<title>[COLOR gold][B]Ep16: Xeque-Mate [/B][/COLOR]</title>
<link>http://vd.ec.cx/vd/dd/RC/RCServer01/videos/SMLLVLT09EP16.mp4</link>
<thumbnail>http://i.imgur.com/5htLqHK.jpg</thumbnail>
<fanart>https://goo.gl/fBFyWB</fanart>
<info>[COLOR blue]Uma interpretação da história de Superman mostra o jovem Clark Kent aprendendo a usar seus superpoderes em Kansas.[/COLOR]</info>
</item>


<item>
<title>[COLOR gold][B]Ep17: Atualização [/B][/COLOR]</title>
<link>http://vd.ec.cx/vd/dd/RC/RCServer01/videos/SMLLVLT09EP17.mp4</link>
<thumbnail>http://i.imgur.com/5htLqHK.jpg</thumbnail>
<fanart>https://goo.gl/fBFyWB</fanart>
<info>[COLOR blue]Uma interpretação da história de Superman mostra o jovem Clark Kent aprendendo a usar seus superpoderes em Kansas.[/COLOR]</info>
</item>


<item>
<title>[COLOR gold][B]Ep18: Charada [/B][/COLOR]</title>
<link>http://vd.ec.cx/vd/dd/RC/RCServer01/videos/SMLLVLT09EP18.mp4</link>
<thumbnail>http://i.imgur.com/5htLqHK.jpg</thumbnail>
<fanart>https://goo.gl/fBFyWB</fanart>
<info>[COLOR blue]Uma interpretação da história de Superman mostra o jovem Clark Kent aprendendo a usar seus superpoderes em Kansas.[/COLOR]</info>
</item>


<item>
<title>[COLOR gold][B]Ep19: Sacrifício [/B][/COLOR]</title>
<link>http://vd.ec.cx/vd/dd/RC/RCServer01/videos/SMLLVLT09EP19.mp4</link>
<thumbnail>http://i.imgur.com/5htLqHK.jpg</thumbnail>
<fanart>https://goo.gl/fBFyWB</fanart>
<info>[COLOR blue]Uma interpretação da história de Superman mostra o jovem Clark Kent aprendendo a usar seus superpoderes em Kansas.[/COLOR]</info>
</item>


<item>
<title>[COLOR gold][B]Ep20: Refém [/B][/COLOR]</title>
<link>http://vd.ec.cx/vd/dd/RC/RCServer01/videos/SMLLVLT09EP20.mp4</link>
<thumbnail>http://i.imgur.com/5htLqHK.jpg</thumbnail>
<fanart>https://goo.gl/fBFyWB</fanart>
<info>[COLOR blue]Uma interpretação da história de Superman mostra o jovem Clark Kent aprendendo a usar seus superpoderes em Kansas.[/COLOR]</info>
</item>


<item>
<title>[COLOR gold][B]Ep21: Salvação [/B][/COLOR]</title>
<link>http://vd.ec.cx/vd/dd/RC/RCServer01/videos/SMLLVLT09EP21.mp4</link>
<thumbnail>http://i.imgur.com/5htLqHK.jpg</thumbnail>
<fanart>https://goo.gl/fBFyWB</fanart>
<info>[COLOR blue]Uma interpretação da história de Superman mostra o jovem Clark Kent aprendendo a usar seus superpoderes em Kansas.[/COLOR]</info>
</item>